aldryn_django_cms/__init__.py
aldryn_django_cms/models.py
aldryn_django_cms/urls.py
aldryn_django_cms/urls_i18n.py
aldryn_django_cms/utils.py
aldryn_django_cms/views.py
tests/__init__.py
tests/settings.py
tests/test_migrations.py
aldryn_django_cms-4.0.1.19.dist-info/LICENSE
aldryn_django_cms-4.0.1.19.dist-info/METADATA
aldryn_django_cms-4.0.1.19.dist-info/WHEEL
aldryn_django_cms-4.0.1.19.dist-info/top_level.txt
aldryn_django_cms-4.0.1.19.dist-info/RECORD
