Metadata-Version: 2.1
Name: aldryn_django_cms
Version: 4.0.1.19
Summary: An opinionated django CMS setup bundled as an Divio Cloud addon
Home-page: https://github.com/divio/aldryn-django-cms
Author: Divio AG
Author-email: info@divio.ch
License: BSD-3-Clause
Classifier: Development Status :: 5 - Production/Stable
Classifier: Environment :: Web Environment
Classifier: Intended Audience :: Developers
Classifier: License :: OSI Approved :: BSD License
Classifier: Operating System :: OS Independent
Classifier: Framework :: Django
Classifier: Framework :: Django :: 3.2
Classifier: Framework :: Django :: 4.2
Classifier: Programming Language :: Python
Classifier: Programming Language :: Python :: 3
Classifier: Programming Language :: Python :: 3.9
Classifier: Programming Language :: Python :: 3.10
Classifier: Programming Language :: Python :: 3.11
Classifier: Topic :: Internet :: WWW/HTTP
Classifier: Topic :: Internet :: WWW/HTTP :: Dynamic Content
Classifier: Topic :: Software Development
Classifier: Topic :: Software Development :: Libraries
License-File: LICENSE
Requires-Dist: django-cms ==4.0.1.dev7
Requires-Dist: aldryn-addons
Requires-Dist: requests
Requires-Dist: django-treebeard >=4.0.1
Requires-Dist: djangocms-admin-style
Requires-Dist: django-select2 >=6.2
Requires-Dist: aldryn-snake
Requires-Dist: django-compressor
Requires-Dist: django-parler
Requires-Dist: django-sortedm2m >=1.5.0
Requires-Dist: django-robots
Requires-Dist: django-simple-captcha <=0.5.20
Requires-Dist: lxml
Requires-Dist: YURL
